[
  [
    {
      "chapters": 197,
      "countries": 56,
      "city": 194,
      "members": 80910,
      "past_events": 2941,
      "upcoming_events": 55,
      "avgchapter": 3,
      "avgevent": 14,
      "avgmember": 410
    }
  ],
  [
    {
      "latinAm": 53,
      "us_can": 58,
      "eur": 49,
      "afr": 11,
      "asia": 17,
      "aus": 9,
      "latinAm_m": 20893,
      "us_can_m": 25814,
      "eur_m": 21896,
      "afr_m": 3458,
      "asia_m": 4240,
      "aus_m": 4609
    }
  ]
]
