[
  [
    {
      "chapters": 193,
      "countries": 52,
      "city": 190,
      "members": 65657,
      "past_events": 2218,
      "upcoming_events": 37,
      "avgchapter": 3,
      "avgevent": 11,
      "avgmember": 340
    }
  ],
  [
    {
      "latinAm": 45,
      "us_can": 60,
      "eur": 56,
      "afr": 9,
      "asia": 14,
      "aus": 9,
      "latinAm_m": 13801,
      "us_can_m": 21361,
      "eur_m": 20626,
      "afr_m": 2441,
      "asia_m": 3585,
      "aus_m": 3843
    }
  ]
]
