[
  [
    {
      "chapters": 198,
      "countries": 56,
      "city": 195,
      "members": 83304,
      "past_events": 3046,
      "upcoming_events": 71,
      "avgchapter": 3,
      "avgevent": 15,
      "avgmember": 420
    }
  ],
  [
    {
      "latinAm": 53,
      "us_can": 58,
      "eur": 50,
      "afr": 11,
      "asia": 17,
      "aus": 9,
      "latinAm_m": 21335,
      "us_can_m": 26449,
      "eur_m": 22469,
      "afr_m": 3831,
      "asia_m": 4577,
      "aus_m": 4643
    }
  ]
]
