[
  [
    {
      "chapters": 197,
      "countries": 56,
      "city": 194,
      "members": 80933,
      "past_events": 2942,
      "upcoming_events": 56,
      "avgchapter": 3,
      "avgevent": 14,
      "avgmember": 410
    }
  ],
  [
    {
      "latinAm": 53,
      "us_can": 58,
      "eur": 49,
      "afr": 11,
      "asia": 17,
      "aus": 9,
      "latinAm_m": 20898,
      "us_can_m": 25822,
      "eur_m": 21897,
      "afr_m": 3464,
      "asia_m": 4242,
      "aus_m": 4610
    }
  ]
]
