[
  [
    {
      "chapters": 926,
      "countries": 86,
      "city": 416,
      "members": 720149,
      "past_events": 18416,
      "upcoming_events": 572,
      "avgchapter": 10,
      "avgevent": 19,
      "avgmember": 777,
      "last_update": "Mon Feb 17 11:25:45 2020"
    }
  ],
  [
    {
      "latinAm": 97,
      "us_can": 339,
      "eur": 292,
      "afr": 39,
      "asia": 127,
      "aus": 32,
      "latinAm_m": 48987,
      "us_can_m": 312439,
      "eur_m": 210721,
      "afr_m": 18513,
      "asia_m": 102317,
      "aus_m": 27172
    }
  ]
]
