[
  [
    {
      "chapters": 901,
      "countries": 87,
      "city": 414,
      "members": 742182,
      "past_events": 20643,
      "upcoming_events": 595,
      "avgchapter": 10,
      "avgevent": 22,
      "avgmember": 823,
      "last_update": "Tue Aug 25 14:59:00 2020"
    }
  ],
  [
    {
      "latinAm": 108,
      "us_can": 317,
      "eur": 283,
      "afr": 40,
      "asia": 122,
      "aus": 31,
      "latinAm_m": 55664,
      "us_can_m": 321312,
      "eur_m": 214816,
      "afr_m": 20534,
      "asia_m": 102451,
      "aus_m": 27405
    }
  ]
]
