[
  [
    {
      "chapters": 923,
      "countries": 83,
      "city": 405,
      "members": 724655,
      "past_events": 18651,
      "upcoming_events": 466,
      "avgchapter": 11,
      "avgevent": 20,
      "avgmember": 785,
      "last_update": "Sat Apr  4 13:20:08 2020"
    }
  ],
  [
    {
      "latinAm": 95,
      "us_can": 333,
      "eur": 296,
      "afr": 38,
      "asia": 130,
      "aus": 31,
      "latinAm_m": 49780,
      "us_can_m": 311979,
      "eur_m": 212153,
      "afr_m": 18701,
      "asia_m": 105273,
      "aus_m": 26769
    }
  ]
]
