[
  [
    {
      "chapters": 923,
      "countries": 86,
      "city": 416,
      "members": 717541,
      "past_events": 18365,
      "upcoming_events": 550,
      "avgchapter": 10,
      "avgevent": 19,
      "avgmember": 777,
      "last_update": "Wed Feb 12 11:23:26 2020"
    }
  ],
  [
    {
      "latinAm": 97,
      "us_can": 338,
      "eur": 292,
      "afr": 38,
      "asia": 126,
      "aus": 32,
      "latinAm_m": 48608,
      "us_can_m": 311630,
      "eur_m": 210069,
      "afr_m": 18429,
      "asia_m": 101707,
      "aus_m": 27098
    }
  ]
]
