[
  [
    {
      "chapters": 887,
      "countries": 84,
      "city": 408,
      "members": 757708,
      "past_events": 22783,
      "upcoming_events": 247,
      "avgchapter": 10,
      "avgevent": 25,
      "avgmember": 854,
      "last_update": "Sat Dec 19 16:12:14 2020"
    }
  ],
  [
    {
      "latinAm": 104,
      "us_can": 318,
      "eur": 281,
      "afr": 41,
      "asia": 112,
      "aus": 31,
      "latinAm_m": 59166,
      "us_can_m": 330523,
      "eur_m": 221420,
      "afr_m": 20741,
      "asia_m": 98799,
      "aus_m": 27059
    }
  ]
]
