[
  [
    {
      "chapters": 616,
      "countries": 73,
      "city": 344,
      "members": 492347,
      "past_events": 13107,
      "upcoming_events": 275,
      "avgchapter": 8,
      "avgevent": 21,
      "avgmember": 799,
      "last_update": "Wed Aug  7 09:59:46 2019"
    }
  ],
  [
    {
      "latinAm": 74,
      "us_can": 239,
      "eur": 188,
      "afr": 21,
      "asia": 67,
      "aus": 27,
      "latinAm_m": 33988,
      "us_can_m": 241019,
      "eur_m": 133175,
      "afr_m": 10502,
      "asia_m": 55207,
      "aus_m": 18456
    }
  ]
]
